{
  "version": "0.2",
  "language": "en",
  "useGitignore": true,
  "files": [
    "**/*"
  ],
  "ignorePaths": [
    "node_modules/**",
    ".next/**",
    "dist/**",
    "build/**",
    ".vercel/**"
  ],
  "words": [
    "Atul",
    "Bengaluru",
    "Bommanahalli",
    "conname",
    "Devarachikanahalli",
    "Devarachiknahalli",
    "fkey",
    "hostnames",
    "initdb",
    "inotify",
    "isready",
    "itemsforsale",
    "Jayanagar",
    "Karnataka",
    "Koramangala",
    "Kumar",
    "Mangaluru",
    "mysuru",
    "Nadu",
    "normalise",
    "OLX",
    "overengineering",
    "pgcrypto",
    "pkey",
    "Supabase",
    "tamilnadu",
    "telangana",
    "Turbopack",
    "Vercel",
    "WATCHPACK"
  ]
}
